README.txt
setup.py
collective/__init__.py
collective.classification.egg-info/PKG-INFO
collective.classification.egg-info/SOURCES.txt
collective.classification.egg-info/dependency_links.txt
collective.classification.egg-info/entry_points.txt
collective.classification.egg-info/namespace_packages.txt
collective.classification.egg-info/not-zip-safe
collective.classification.egg-info/requires.txt
collective.classification.egg-info/top_level.txt
collective/classification/__init__.py
collective/classification/configure.zcml
collective/classification/interfaces.py
collective/classification/subscribers.py
collective/classification/adapters/__init__.py
collective/classification/adapters/atcontenttypes.py
collective/classification/adapters/configure.zcml
collective/classification/browser/__init__.py
collective/classification/browser/classificationstats.pt
collective/classification/browser/classificationstats.py
collective/classification/browser/clusterize.pt
collective/classification/browser/clusterize.py
collective/classification/browser/configure.zcml
collective/classification/browser/controlpanel.py
collective/classification/browser/samplecontent.py
collective/classification/browser/suggestcategories.py
collective/classification/browser/terms.pt
collective/classification/browser/terms.py
collective/classification/classifiers/__init__.py
collective/classification/classifiers/clustering.py
collective/classification/classifiers/nounbayesclassifier.py
collective/classification/classifiers/npextractor.py
collective/classification/classifiers/npstorage.py
collective/classification/classifiers/utils.py
collective/classification/nltkutilities/__init__.py
collective/classification/nltkutilities/configure.zcml
collective/classification/nltkutilities/downloader.py
collective/classification/nltkutilities/tagger.py
collective/classification/nltkutilities/tokenizer.py
collective/classification/profiles/default/componentregistry.xml
collective/classification/profiles/default/controlpanel.xml
collective/classification/profiles/default/metadata.xml
collective/classification/tests/__init__.py
collective/classification/tests/base.py
collective/classification/tests/integration.txt
collective/classification/tests/layer.py
collective/classification/tests/test_adapters.py
collective/classification/tests/test_clustering.py
collective/classification/tests/test_doctests.py
