Metadata-Version: 1.0
Name: collective.classification
Version: 0.1a3
Summary: Content classification/clustering through language processing
Home-page: http://github.org/ggozad/collective.classification
Author: Yiorgis Gozadinos
Author-email: ggozad@jarn.com
License: GPL
Keywords: term-extract,semantic,classification,Parts-Of-Speech,tagging,plone
Platform: UNKNOWN
Classifier: Environment :: Web Environment
Classifier: Framework :: Plone
Classifier: Intended Audience :: Developers
Classifier: Intended Audience :: Science/Research
Classifier: License :: OSI Approved :: GNU General Public License (GPL)
Classifier: Operating System :: OS Independent
Classifier: Programming Language :: Python
Classifier: Topic :: Software Development :: Libraries :: Python Modules
Classifier: Topic :: Scientific/Engineering :: Artificial Intelligence
Classifier: Topic :: Scientific/Engineering :: Information Analysis
Classifier: Topic :: Text Processing :: Filters
Classifier: Topic :: Text Processing :: General
Classifier: Topic :: Text Processing :: Indexing
